typechecker/Typecheck.py
typechecker/__init__.py
typechecker/decorator.py
pytypechecker-1.0.4.dist-info/LICENCE.txt
pytypechecker-1.0.4.dist-info/METADATA
pytypechecker-1.0.4.dist-info/WHEEL
pytypechecker-1.0.4.dist-info/top_level.txt
pytypechecker-1.0.4.dist-info/RECORD
