Metadata-Version: 2.1
Name: pytypechecker
Version: 1.0.4
Summary: Includes decorator "@typecheck" to provide type check on run-time.
Home-page: https://github.com/sondrekh/python_typechecker
Author: Sondre Kværne Hansen
Author-email: sondrekhansen+pypi@gmail.com
License: LICENCE.txt
License-File: LICENCE.txt
